LICENSE
README.md
setup.py
zerionPy/__init__.py
zerionPy/ifb.py
zerionPy.egg-info/PKG-INFO
zerionPy.egg-info/SOURCES.txt
zerionPy.egg-info/dependency_links.txt
zerionPy.egg-info/not-zip-safe
zerionPy.egg-info/requires.txt
zerionPy.egg-info/top_level.txt