Metadata-Version: 2.1
Name: zerionPy
Version: 1.0.0
Summary: Zerion Software API Wrapper
Home-page: https://github.com/jhsu98/zerion-py
Author: Jonathan Hsu
Author-email: jhsu98@gmail.com
License: MIT
Platform: UNKNOWN
Requires-Python: >=3.10
License-File: LICENSE
